neon_tts_plugin_mozilla_local/__init__.py
neon_tts_plugin_mozilla_local-0.2.0.dist-info/LICENSE.md
neon_tts_plugin_mozilla_local-0.2.0.dist-info/METADATA
neon_tts_plugin_mozilla_local-0.2.0.dist-info/WHEEL
neon_tts_plugin_mozilla_local-0.2.0.dist-info/entry_points.txt
neon_tts_plugin_mozilla_local-0.2.0.dist-info/top_level.txt
neon_tts_plugin_mozilla_local-0.2.0.dist-info/zip-safe
neon_tts_plugin_mozilla_local-0.2.0.dist-info/RECORD
