Metadata-Version: 2.1
Name: neon-tts-plugin-mozilla-local
Version: 0.2.0
Summary: A Mozilla TTS plugin for Neon
Home-page: https://github.com/NeonGeckoCom/neon-tts-plugin-mozilla_local
Author: Neongecko
Author-email: developers@neon.ai
License: NeonAI License v1.0
Keywords: mycroft plugin tts
Platform: UNKNOWN
Classifier: Intended Audience :: Developers
Classifier: Topic :: Text Processing :: Linguistic
Classifier: Programming Language :: Python :: 3.6
Requires-Dist: TTS (~=0.3.1)
Requires-Dist: neon-utils (>=0.5.7)
